metobs_toolkit/__init__.py
metobs_toolkit/analysis.py
metobs_toolkit/backend_collection/argumentcheckers.py
metobs_toolkit/backend_collection/dataframe_constructors.py
metobs_toolkit/backend_collection/datetime_agg_collection.py
metobs_toolkit/backend_collection/datetime_collection.py
metobs_toolkit/backend_collection/decorators.py
metobs_toolkit/backend_collection/dev_collection.py
metobs_toolkit/backend_collection/df_helpers.py
metobs_toolkit/backend_collection/errorclasses.py
metobs_toolkit/backend_collection/filter_modeldatadf.py
metobs_toolkit/backend_collection/loggingmodule.py
metobs_toolkit/backend_collection/printing_collection.py
metobs_toolkit/backend_collection/uniqueness.py
metobs_toolkit/datafiles/demo_datafile.csv
metobs_toolkit/datafiles/demo_metadatafile.csv
metobs_toolkit/datafiles/demo_template.json
metobs_toolkit/dataset.py
metobs_toolkit/gap.py
metobs_toolkit/gee_api.py
metobs_toolkit/geedatasetmanagers.py
metobs_toolkit/geometry_functions.py
metobs_toolkit/gf_collection/debias_gapfill.py
metobs_toolkit/gf_collection/diurnal_debias_gapfill.py
metobs_toolkit/gf_collection/gf_common_methods.py
metobs_toolkit/gf_collection/overview_df_constructors.py
metobs_toolkit/io_collection/dataparser.py
metobs_toolkit/io_collection/filereaders.py
metobs_toolkit/io_collection/filewriters.py
metobs_toolkit/io_collection/metadataparser.py
metobs_toolkit/modeltimeseries.py
metobs_toolkit/obstypes.py
metobs_toolkit/plot_collection/__init__.py
metobs_toolkit/plot_collection/cycle_plotting.py
metobs_toolkit/plot_collection/folium_spatial.py
metobs_toolkit/plot_collection/general_functions.py
metobs_toolkit/plot_collection/pd_basic_plotting.py
metobs_toolkit/plot_collection/qc_info_pies.py
metobs_toolkit/plot_collection/timeseries_plotting.py
metobs_toolkit/qc_collection/__init__.py
metobs_toolkit/qc_collection/buddy_check.py
metobs_toolkit/qc_collection/common_functions.py
metobs_toolkit/qc_collection/distancematrix_func.py
metobs_toolkit-1.0.0.dist-info/METADATA
metobs_toolkit-1.0.0.dist-info/WHEEL
metobs_toolkit-1.0.0.dist-info/licenses/LICENSE
metobs_toolkit-1.0.0.dist-info/RECORD
