Metadata-Version: 2.4
Name: MetObs-toolkit
Version: 1.0.0
Summary: A Meteorological observations toolkit for scientists
License: LICENSE
License-File: LICENSE
Keywords: meteorology,observations,urban climate
Author: Thomas Vergauwen
Author-email: thomas.vergauwen@ugent.be
Requires-Python: >=3.10,<4.0
Classifier: Development Status :: 5 - Production/Stable
Classifier: Intended Audience :: Science/Research
Classifier: License :: OSI Approved :: MIT License
Classifier: Natural Language :: English
Classifier: Operating System :: OS Independent
Classifier: Programming Language :: Python :: 3
Classifier: Programming Language :: Python :: 3.10
Classifier: Programming Language :: Python :: 3.11
Classifier: Programming Language :: Python :: 3.12
Classifier: Programming Language :: Python :: 3.13
Classifier: Programming Language :: Python :: 3.14
Classifier: Topic :: Scientific/Engineering :: Atmospheric Science
Requires-Dist: cartopy (>=0.23)
Requires-Dist: earthengine-api (<=1.6.11)
Requires-Dist: geemap (>=0.35.3)
Requires-Dist: geopandas (>=1.0.1)
Requires-Dist: mapclassify (>=2.8.1)
Requires-Dist: matplotlib (>=3.9.2)
Requires-Dist: netcdf4 (>=1.7.2,<2.0.0)
Requires-Dist: numpy (>=1)
Requires-Dist: pandas (>=2)
Requires-Dist: pint (>=0.24.4)
Requires-Dist: pyarrow (>=21.0.0,<22.0.0)
Requires-Dist: setuptools (>=78.1.0)
Requires-Dist: shapely (>=2.0.6)
Requires-Dist: xarray (>=2022.3.0)
